rtl/adder_rca.v
`default_nettype none
`timescale 1ns/1ps

module adder_rca
#(
    parameter WIDTH = 8
)
(
    input  signed [WIDTH-1:0] a,
    input  signed [WIDTH-1:0] b,
    output signed [WIDTH-1:0] sum,
    output                    overflow
);

    wire [WIDTH:0] carry;

    assign carry[0] = 1'b0;

    genvar i;
    generate
        for (i = 0; i < WIDTH; i = i + 1) begin : gen_rca_stage
            // Ripple-carry full adder stage; sum naturally wraps to WIDTH bits.
            assign sum[i]      = a[i] ^ b[i] ^ carry[i];
            assign carry[i+1]  = (a[i] & b[i]) |
                                 (a[i] & carry[i]) |
                                 (b[i] & carry[i]);
        end
    endgenerate

    // Signed overflow occurs when carry into and out of the sign bit differ.
    assign overflow = carry[WIDTH] ^ carry[WIDTH-1];

endmodule

`default_nettype wire

tb/tb_adder_rca.v
`timescale 1ns/1ps

module tb_adder_rca;

    reg signed [7:0]   a8;
    reg signed [7:0]   b8;
    wire signed [7:0]  sum8;
    wire               overflow8;

    reg signed [15:0]  a16;
    reg signed [15:0]  b16;
    wire signed [15:0] sum16;
    wire               overflow16;

    reg signed [31:0]  a32;
    reg signed [31:0]  b32;
    wire signed [31:0] sum32;
    wire               overflow32;

    integer tests_run;
    integer errors;

    adder_rca
    #(
        .WIDTH(8)
    )
    dut8
    (
        .a(a8),
        .b(b8),
        .sum(sum8),
        .overflow(overflow8)
    );

    adder_rca
    #(
        .WIDTH(16)
    )
    dut16
    (
        .a(a16),
        .b(b16),
        .sum(sum16),
        .overflow(overflow16)
    );

    adder_rca
    #(
        .WIDTH(32)
    )
    dut32
    (
        .a(a32),
        .b(b32),
        .sum(sum32),
        .overflow(overflow32)
    );

    task check8;
        input signed [7:0] a_val;
        input signed [7:0] b_val;
        input signed [7:0] expected_sum;
        input              expected_overflow;
        begin
            a8 = a_val;
            b8 = b_val;
            #1;
            tests_run = tests_run + 1;
            if ((sum8 !== expected_sum) || (overflow8 !== expected_overflow)) begin
                errors = errors + 1;
                $display("FAIL WIDTH=8  a=%0d b=%0d sum=%0d overflow=%0b expected_sum=%0d expected_overflow=%0b",
                         a_val, b_val, sum8, overflow8, expected_sum, expected_overflow);
            end else begin
                $display("PASS WIDTH=8  a=%0d b=%0d sum=%0d overflow=%0b",
                         a_val, b_val, sum8, overflow8);
            end
        end
    endtask

    task check16;
        input signed [15:0] a_val;
        input signed [15:0] b_val;
        input signed [15:0] expected_sum;
        input               expected_overflow;
        begin
            a16 = a_val;
            b16 = b_val;
            #1;
            tests_run = tests_run + 1;
            if ((sum16 !== expected_sum) || (overflow16 !== expected_overflow)) begin
                errors = errors + 1;
                $display("FAIL WIDTH=16 a=%0d b=%0d sum=%0d overflow=%0b expected_sum=%0d expected_overflow=%0b",
                         a_val, b_val, sum16, overflow16, expected_sum, expected_overflow);
            end else begin
                $display("PASS WIDTH=16 a=%0d b=%0d sum=%0d overflow=%0b",
                         a_val, b_val, sum16, overflow16);
            end
        end
    endtask

    task check32;
        input signed [31:0] a_val;
        input signed [31:0] b_val;
        input signed [31:0] expected_sum;
        input               expected_overflow;
        begin
            a32 = a_val;
            b32 = b_val;
            #1;
            tests_run = tests_run + 1;
            if ((sum32 !== expected_sum) || (overflow32 !== expected_overflow)) begin
                errors = errors + 1;
                $display("FAIL WIDTH=32 a=%0d b=%0d sum=%0d overflow=%0b expected_sum=%0d expected_overflow=%0b",
                         a_val, b_val, sum32, overflow32, expected_sum, expected_overflow);
            end else begin
                $display("PASS WIDTH=32 a=%0d b=%0d sum=%0d overflow=%0b",
                         a_val, b_val, sum32, overflow32);
            end
        end
    endtask

    initial begin
        $dumpfile("waveforms/tb_adder_rca.vcd");
        $dumpvars(0, tb_adder_rca);

        tests_run = 0;
        errors    = 0;

        a8  = 8'sd0;
        b8  = 8'sd0;
        a16 = 16'sd0;
        b16 = 16'sd0;
        a32 = 32'sd0;
        b32 = 32'sd0;
        #1;

        check8(8'sd12,       8'sd34,       8'sd46,        1'b0);
        check8(-8'sd12,     -8'sd23,      -8'sd35,        1'b0);
        check8(8'sd100,     -8'sd45,       8'sd55,        1'b0);
        check8(8'sd127,      8'sd1,        8'sh80,        1'b1);
        check8(8'sh80,      -8'sd1,        8'sd127,       1'b1);
        check8(8'sd127,      8'sd127,     -8'sd2,         1'b1);

        check16(16'sd1234,   16'sd4321,    16'sd5555,     1'b0);
        check16(-16'sd1234, -16'sd4321,   -16'sd5555,     1'b0);
        check16(16'sd20000, -16'sd12345,   16'sd7655,     1'b0);
        check16(16'sd32767,  16'sd1,       16'sh8000,     1'b1);
        check16(16'sh8000,  -16'sd1,       16'sd32767,    1'b1);

        check32(32'sd100000,     32'sd200000,      32'sd300000,      1'b0);
        check32(-32'sd100000,   -32'sd200000,     -32'sd300000,      1'b0);
        check32(32'sd123456789, -32'sd98765432,    32'sd24691357,    1'b0);
        check32(32'sh7fffffff,   32'sd1,           32'sh80000000,    1'b1);
        check32(32'sh80000000,  -32'sd1,           32'sh7fffffff,    1'b1);

        if (errors == 0) begin
            $display("ALL TESTS PASSED: tb_adder_rca tests_run=%0d", tests_run);
        end else begin
            $display("TESTS FAILED: tb_adder_rca tests_run=%0d errors=%0d", tests_run, errors);
        end

        $finish;
    end

endmodule

waveforms/tb_adder_rca.vcd
$date
	Sun Jun 07 17:09:24 2026
$end
$version
	Icarus Verilog
$end
$timescale
	1ps
$end
$scope module tb_adder_rca $end
$var wire 8 ! sum8 [7:0] $end
$var wire 32 " sum32 [31:0] $end
$var wire 16 # sum16 [15:0] $end
$var wire 1 $ overflow8 $end
$var wire 1 % overflow32 $end
$var wire 1 & overflow16 $end
$var reg 16 ' a16 [15:0] $end
$var reg 32 ( a32 [31:0] $end
$var reg 8 ) a8 [7:0] $end
$var reg 16 * b16 [15:0] $end
$var reg 32 + b32 [31:0] $end
$var reg 8 , b8 [7:0] $end
$var integer 32 - errors [31:0] $end
$var integer 32 . tests_run [31:0] $end
$scope module dut16 $end
$var wire 16 / a [15:0] $end
$var wire 16 0 b [15:0] $end
$var wire 1 & overflow $end
$var wire 16 1 sum [15:0] $end
$var wire 17 2 carry [16:0] $end
$var parameter 32 3 WIDTH $end
$scope begin gen_rca_stage[0] $end
$var parameter 2 4 i $end
$upscope $end
$scope begin gen_rca_stage[1] $end
$var parameter 2 5 i $end
$upscope $end
$scope begin gen_rca_stage[2] $end
$var parameter 3 6 i $end
$upscope $end
$scope begin gen_rca_stage[3] $end
$var parameter 3 7 i $end
$upscope $end
$scope begin gen_rca_stage[4] $end
$var parameter 4 8 i $end
$upscope $end
$scope begin gen_rca_stage[5] $end
$var parameter 4 9 i $end
$upscope $end
$scope begin gen_rca_stage[6] $end
$var parameter 4 : i $end
$upscope $end
$scope begin gen_rca_stage[7] $end
$var parameter 4 ; i $end
$upscope $end
$scope begin gen_rca_stage[8] $end
$var parameter 5 < i $end
$upscope $end
$scope begin gen_rca_stage[9] $end
$var parameter 5 = i $end
$upscope $end
$scope begin gen_rca_stage[10] $end
$var parameter 5 > i $end
$upscope $end
$scope begin gen_rca_stage[11] $end
$var parameter 5 ? i $end
$upscope $end
$scope begin gen_rca_stage[12] $end
$var parameter 5 @ i $end
$upscope $end
$scope begin gen_rca_stage[13] $end
$var parameter 5 A i $end
$upscope $end
$scope begin gen_rca_stage[14] $end
$var parameter 5 B i $end
$upscope $end
$scope begin gen_rca_stage[15] $end
$var parameter 5 C i $end
$upscope $end
$upscope $end
$scope module dut32 $end
$var wire 32 D a [31:0] $end
$var wire 32 E b [31:0] $end
$var wire 1 % overflow $end
$var wire 32 F sum [31:0] $end
$var wire 33 G carry [32:0] $end
$var parameter 32 H WIDTH $end
$scope begin gen_rca_stage[0] $end
$var parameter 2 I i $end
$upscope $end
$scope begin gen_rca_stage[1] $end
$var parameter 2 J i $end
$upscope $end
$scope begin gen_rca_stage[2] $end
$var parameter 3 K i $end
$upscope $end
$scope begin gen_rca_stage[3] $end
$var parameter 3 L i $end
$upscope $end
$scope begin gen_rca_stage[4] $end
$var parameter 4 M i $end
$upscope $end
$scope begin gen_rca_stage[5] $end
$var parameter 4 N i $end
$upscope $end
$scope begin gen_rca_stage[6] $end
$var parameter 4 O i $end
$upscope $end
$scope begin gen_rca_stage[7] $end
$var parameter 4 P i $end
$upscope $end
$scope begin gen_rca_stage[8] $end
$var parameter 5 Q i $end
$upscope $end
$scope begin gen_rca_stage[9] $end
$var parameter 5 R i $end
$upscope $end
$scope begin gen_rca_stage[10] $end
$var parameter 5 S i $end
$upscope $end
$scope begin gen_rca_stage[11] $end
$var parameter 5 T i $end
$upscope $end
$scope begin gen_rca_stage[12] $end
$var parameter 5 U i $end
$upscope $end
$scope begin gen_rca_stage[13] $end
$var parameter 5 V i $end
$upscope $end
$scope begin gen_rca_stage[14] $end
$var parameter 5 W i $end
$upscope $end
$scope begin gen_rca_stage[15] $end
$var parameter 5 X i $end
$upscope $end
$scope begin gen_rca_stage[16] $end
$var parameter 6 Y i $end
$upscope $end
$scope begin gen_rca_stage[17] $end
$var parameter 6 Z i $end
$upscope $end
$scope begin gen_rca_stage[18] $end
$var parameter 6 [ i $end
$upscope $end
$scope begin gen_rca_stage[19] $end
$var parameter 6 \ i $end
$upscope $end
$scope begin gen_rca_stage[20] $end
$var parameter 6 ] i $end
$upscope $end
$scope begin gen_rca_stage[21] $end
$var parameter 6 ^ i $end
$upscope $end
$scope begin gen_rca_stage[22] $end
$var parameter 6 _ i $end
$upscope $end
$scope begin gen_rca_stage[23] $end
$var parameter 6 ` i $end
$upscope $end
$scope begin gen_rca_stage[24] $end
$var parameter 6 a i $end
$upscope $end
$scope begin gen_rca_stage[25] $end
$var parameter 6 b i $end
$upscope $end
$scope begin gen_rca_stage[26] $end
$var parameter 6 c i $end
$upscope $end
$scope begin gen_rca_stage[27] $end
$var parameter 6 d i $end
$upscope $end
$scope begin gen_rca_stage[28] $end
$var parameter 6 e i $end
$upscope $end
$scope begin gen_rca_stage[29] $end
$var parameter 6 f i $end
$upscope $end
$scope begin gen_rca_stage[30] $end
$var parameter 6 g i $end
$upscope $end
$scope begin gen_rca_stage[31] $end
$var parameter 6 h i $end
$upscope $end
$upscope $end
$scope module dut8 $end
$var wire 8 i a [7:0] $end
$var wire 8 j b [7:0] $end
$var wire 1 $ overflow $end
$var wire 8 k sum [7:0] $end
$var wire 9 l carry [8:0] $end
$var parameter 32 m WIDTH $end
$scope begin gen_rca_stage[0] $end
$var parameter 2 n i $end
$upscope $end
$scope begin gen_rca_stage[1] $end
$var parameter 2 o i $end
$upscope $end
$scope begin gen_rca_stage[2] $end
$var parameter 3 p i $end
$upscope $end
$scope begin gen_rca_stage[3] $end
$var parameter 3 q i $end
$upscope $end
$scope begin gen_rca_stage[4] $end
$var parameter 4 r i $end
$upscope $end
$scope begin gen_rca_stage[5] $end
$var parameter 4 s i $end
$upscope $end
$scope begin gen_rca_stage[6] $end
$var parameter 4 t i $end
$upscope $end
$scope begin gen_rca_stage[7] $end
$var parameter 4 u i $end
$upscope $end
$upscope $end
$scope task check16 $end
$var reg 16 v a_val [15:0] $end
$var reg 16 w b_val [15:0] $end
$var reg 1 x expected_overflow $end
$var reg 16 y expected_sum [15:0] $end
$upscope $end
$scope task check32 $end
$var reg 32 z a_val [31:0] $end
$var reg 32 { b_val [31:0] $end
$var reg 1 | expected_overflow $end
$var reg 32 } expected_sum [31:0] $end
$upscope $end
$scope task check8 $end
$var reg 8 ~ a_val [7:0] $end
$var reg 8 !" b_val [7:0] $end
$var reg 1 "" expected_overflow $end
$var reg 8 #" expected_sum [7:0] $end
$upscope $end
$upscope $end
$enddefinitions $end
$comment Show the parameter values. $end
$dumpall
b111 u
b110 t
b101 s
b100 r
b11 q
b10 p
b1 o
b0 n
b1000 m
b11111 h
b11110 g
b11101 f
b11100 e
b11011 d
b11010 c
b11001 b
b11000 a
b10111 `
b10110 _
b10101 ^
b10100 ]
b10011 \
b10010 [
b10001 Z
b10000 Y
b1111 X
b1110 W
b1101 V
b1100 U
b1011 T
b1010 S
b1001 R
b1000 Q
b111 P
b110 O
b101 N
b100 M
b11 L
b10 K
b1 J
b0 I
b100000 H
b1111 C
b1110 B
b1101 A
b1100 @
b1011 ?
b1010 >
b1001 =
b1000 <
b111 ;
b110 :
b101 9
b100 8
b11 7
b10 6
b1 5
b0 4
b10000 3
$end
#0
$dumpvars
bx #"
x""
bx !"
bx ~
bx }
x|
bx {
bx z
bx y
xx
bx w
bx v
b0 l
b0 k
b0 j
b0 i
b0 G
b0 F
b0 E
b0 D
b0 2
b0 1
b0 0
b0 /
b0 .
b0 -
b0 ,
b0 +
b0 *
b0 )
b0 (
b0 '
0&
0%
0$
b0 #
b0 "
b0 !
$end
#1000
b101110 !
b101110 k
b100010 ,
b100010 j
b1100 )
b1100 i
0""
b101110 #"
b100010 !"
b1100 ~
#2000
b111000000 l
b11011101 !
b11011101 k
b11101001 ,
b11101001 j
b11110100 )
b11110100 i
b11011101 #"
b11101001 !"
b11110100 ~
b1 .
#3000
b110000000 l
b110111 !
b110111 k
b11010011 ,
b11010011 j
b1100100 )
b1100100 i
b110111 #"
b11010011 !"
b1100100 ~
b10 .
#4000
1$
b11111110 l
b10000000 !
b10000000 k
b1 ,
b1 j
b1111111 )
b1111111 i
1""
b10000000 #"
b1 !"
b1111111 ~
b11 .
#5000
1$
b100000000 l
b1111111 !
b1111111 k
b11111111 ,
b11111111 j
b10000000 )
b10000000 i
b1111111 #"
b11111111 !"
b10000000 ~
b100 .
#6000
b11111110 l
b11111110 !
b11111110 k
b1111111 ,
b1111111 j
b1111111 )
b1111111 i
b11111110 #"
b1111111 !"
b1111111 ~
b101 .
#7000
b110000000 2
b1010110110011 #
b1010110110011 1
b1000011100001 *
b1000011100001 0
b10011010010 '
b10011010010 /
0x
b1010110110011 y
b1000011100001 w
b10011010010 v
b110 .
#8000
b1110101001001101 #
b1110101001001101 1
b11111111001111100 2
b1110111100011111 *
b1110111100011111 0
b1111101100101110 '
b1111101100101110 /
b1110101001001101 y
b1110111100011111 w
b1111101100101110 v
b111 .
#9000
b11001110000000000 2
b1110111100111 #
b1110111100111 1
b1100111111000111 *
b1100111111000111 0
b100111000100000 '
b100111000100000 /
b1110111100111 y
b1100111111000111 w
b100111000100000 v
b1000 .
#10000
1&
b1111111111111110 2
b1000000000000000 #
b1000000000000000 1
b1 *
b1 0
b111111111111111 '
b111111111111111 /
1x
b1000000000000000 y
b1 w
b111111111111111 v
b1001 .
#11000
1&
b10000000000000000 2
b111111111111111 #
b111111111111111 1
b1111111111111111 *
b1111111111111111 0
b1000000000000000 '
b1000000000000000 /
b111111111111111 y
b1111111111111111 w
b1000000000000000 v
b1010 .
#12000
b1100001100000000000 G
b1001001001111100000 "
b1001001001111100000 F
b110000110101000000 +
b110000110101000000 E
b11000011010100000 (
b11000011010100000 D
0|
b1001001001111100000 }
b110000110101000000 {
b11000011010100000 z
b1011 .
#13000
b111111111111110011110011110000000 G
b11111111111110110110110000100000 "
b11111111111110110110110000100000 F
b11111111111111001111001011000000 +
b11111111111111001111001011000000 E
b11111111111111100111100101100000 (
b11111111111111100111100101100000 D
b11111111111110110110110000100000 }
b11111111111111001111001011000000 {
b11111111111111100111100101100000 z
b1100 .
#14000
b111111100001111111111101000000000 G
b1011110001100001010011101 "
b1011110001100001010011101 F
b11111010000111001111010110001000 +
b11111010000111001111010110001000 E
b111010110111100110100010101 (
b111010110111100110100010101 D
b1011110001100001010011101 }
b11111010000111001111010110001000 {
b111010110111100110100010101 z
b1101 .
#15000
1%
b11111111111111111111111111111110 G
b10000000000000000000000000000000 "
b10000000000000000000000000000000 F
b1 +
b1 E
b1111111111111111111111111111111 (
b1111111111111111111111111111111 D
1|
b10000000000000000000000000000000 }
b1 {
b1111111111111111111111111111111 z
b1110 .
#16000
1%
b100000000000000000000000000000000 G
b1111111111111111111111111111111 "
b1111111111111111111111111111111 F
b11111111111111111111111111111111 +
b11111111111111111111111111111111 E
b10000000000000000000000000000000 (
b10000000000000000000000000000000 D
b1111111111111111111111111111111 }
b11111111111111111111111111111111 {
b10000000000000000000000000000000 z
b1111 .
#17000
b10000 .
